algorithms_ai/__init__.py
algorithms_ai/data/__init__.py
algorithms_ai/data/analysis/__init__.py
algorithms_ai/data/processor/__init__.py
algorithms_ai/data/processor/consts.py
algorithms_ai/data/processor/html_processor.py
algorithms_ai/data/processor/old.py
algorithms_ai/data/processor/process_ner_labels.py
algorithms_ai/data/processor/process_text.py
algorithms_ai/data/processor/process_token.py
algorithms_ai/data/processor/tokenizer.py
algorithms_ai/data/utils/__init__.py
algorithms_ai/data/utils/text_utils.py
algorithms_ai/data/visualization/__init__.py
algorithms_ai/model/__init__.py
algorithms_ai/model/deploy/__init__.py
algorithms_ai/model/evaluator/__init__.py
algorithms_ai/model/inference/__init__.py
algorithms_ai/model/loss/__init__.py
algorithms_ai/model/mudules/__init__.py
algorithms_ai/model/optimizer/__init__.py
algorithms_ai/model/parameters/__init__.py
algorithms_ai/model/trainer/__init__.py
algorithms_ai/model/usage/__init__.py
algorithms_ai/model/utils/__init__.py
algorithms_ai/utils/__init__.py
algorithms_ai/utils/data_utils.py
algorithms_ai/utils/logs_utils.py
algorithms_ai/utils/cache_utils/__init__.py
algorithms_ai/utils/log_utils/__init__.py
algorithms_ai-0.1.1.dist-info/LICENSE
algorithms_ai-0.1.1.dist-info/METADATA
algorithms_ai-0.1.1.dist-info/WHEEL
algorithms_ai-0.1.1.dist-info/top_level.txt
algorithms_ai-0.1.1.dist-info/RECORD
